kiacopy/__init__.py
kiacopy/best_opt2.py
kiacopy/circuit.py
kiacopy/cli.py
kiacopy/colony.py
kiacopy/grapher.py
kiacopy/parameter.py
kiacopy/plugins.py
kiacopy/solution.py
kiacopy/solver.py
kiacopy/solverplugin.py
kiacopy/state.py
kiacopy/ants/__init__.py
kiacopy/ants/ant.py
kiacopy/ants/randomant.py
kiacopy/ants/sensitiveant.py
kiacopy/utils/__init__.py
kiacopy/utils/data.py
kiacopy/utils/general.py
kiacopy/utils/plot.py
kiacopy-0.3.7.dist-info/AUTHORS.rst
kiacopy-0.3.7.dist-info/LICENSE
kiacopy-0.3.7.dist-info/METADATA
kiacopy-0.3.7.dist-info/WHEEL
kiacopy-0.3.7.dist-info/entry_points.txt
kiacopy-0.3.7.dist-info/top_level.txt
kiacopy-0.3.7.dist-info/RECORD
