Metadata-Version: 2.1
Name: kiacopy
Version: 0.3.7
Summary: kiacopy can make k-independent traveling salesman problem
Home-page: https://github.com/ganariya/kiacopy
Author: ganariya
Author-email: ganariya2525@gmail.com
License: MIT license
Keywords: kiacopy
Platform: UNKNOWN
Classifier: Development Status :: 2 - Pre-Alpha
Classifier: Intended Audience :: Developers
Classifier: License :: OSI Approved :: MIT License
Classifier: Natural Language :: English
Classifier: Programming Language :: Python :: 3
Classifier: Programming Language :: Python :: 3.8
Classifier: Programming Language :: Python :: 3.9
Requires-Python: >=3.5
Requires-Dist: Click (>=7.0)
Requires-Dist: networkx
Requires-Dist: tsplib95
Requires-Dist: numpy
Requires-Dist: matplotlib
Requires-Dist: pandas
Requires-Dist: acopy
